python_pipes/__init__.py
python_pipes/python_pipes.py
python_pipes-0.0.4.dist-info/LICENSE
python_pipes-0.0.4.dist-info/METADATA
python_pipes-0.0.4.dist-info/WHEEL
python_pipes-0.0.4.dist-info/top_level.txt
python_pipes-0.0.4.dist-info/zip-safe
python_pipes-0.0.4.dist-info/RECORD
