Metadata-Version: 2.1
Name: python-pipes
Version: 0.0.4
Summary: Helpers to manage stdin / stdout and UNIX pipes
Home-page: https://github.com/cr0hn/python-pipes
Author: UNKNOWN
Author-email: UNKNOWN
License: License :: OSI Approved :: BSD License
Keywords: unix,pipes,stdin,stderr
Platform: UNKNOWN
Classifier: Programming Language :: Python :: 3.5
Classifier: Programming Language :: Python :: 3.6
Classifier: Programming Language :: Python :: 3.7
Classifier: Programming Language :: Python :: 3.8
